tabulardelta/__init__.py
tabulardelta/py.typed
tabulardelta/tabulardelta.py
tabulardelta/comparators/__init__.py
tabulardelta/comparators/comparator.py
tabulardelta/comparators/pandas_comparator.py
tabulardelta/comparators/sqlcompyre_comparator.py
tabulardelta/comparators/sqlmetadata_comparator.py
tabulardelta/comparators/tabulardelta_dataclasses.py
tabulardelta/formatters/__init__.py
tabulardelta/formatters/detailed_text_formatter.py
tabulardelta/formatters/formatter.py
tabulardelta/formatters/overview_row_formatter.py
tabulardelta/formatters/tabulartext/__init__.py
tabulardelta/formatters/tabulartext/cell.py
tabulardelta/formatters/tabulartext/table.py
tabulardelta-1.1.1.dist-info/licenses/LICENSE
tabulardelta-1.1.1.dist-info/METADATA
tabulardelta-1.1.1.dist-info/WHEEL
tabulardelta-1.1.1.dist-info/top_level.txt
tabulardelta-1.1.1.dist-info/RECORD
