Metadata-Version: 2.4
Name: tabulardelta
Version: 1.1.1
Summary: Simplify table comparisons.
Project-URL: repository, https://github.com/quantco/tabulardelta
Classifier: Programming Language :: Python :: 3
Classifier: Programming Language :: Python :: 3.11
Classifier: Programming Language :: Python :: 3.12
Requires-Python: >=3.11
License-File: LICENSE
Requires-Dist: numpy<3,>=1.24.4
Requires-Dist: pandas<3,>=2.0.3
Dynamic: license-file
